odoo_backup_db_cli/__init__.py
odoo_backup_db_cli/cli.py
odoo_backup_db_cli/db_backup.py
odoo_backup_db_cli/protocols/__init__.py
odoo_backup_db_cli/protocols/ftp.py
odoo_backup_db_cli/protocols/local.py
odoo_backup_db_cli/protocols/sftp.py
odoo_backup_db_cli/py.typed
odoo_backup_db_cli/utils.py
odoo_backup_db_cli-1.0.0.dist-info/entry_points.txt
odoo_backup_db_cli-1.0.0.dist-info/LICENSE
odoo_backup_db_cli-1.0.0.dist-info/WHEEL
odoo_backup_db_cli-1.0.0.dist-info/METADATA
odoo_backup_db_cli-1.0.0.dist-info/RECORD
