Metadata-Version: 2.1
Name: odoo-backup-db-cli
Version: 1.0.0
Summary: Tool to create full backup of odoo database
Home-page: https://github.com/ventor-tech/odoo-backup-db-cli
License: AGPL3
Keywords: odoo,backup,filestore,cli
Author: VentorTech OU
Author-email: hello@ventor.tech
Requires-Python: >=3.6,<3.9
Classifier: Development Status :: 3 - Alpha
Classifier: Intended Audience :: Developers
Classifier: License :: Other/Proprietary License
Classifier: Operating System :: OS Independent
Classifier: Programming Language :: Python :: 3
Classifier: Programming Language :: Python :: 3.6
Classifier: Programming Language :: Python :: 3.7
Classifier: Programming Language :: Python :: 3.8
Classifier: Topic :: Software Development :: Libraries :: Python Modules
Requires-Dist: importlib-metadata (==1.7.0)
Requires-Dist: pysftp (>=0.2.9,<0.3.0)
Requires-Dist: python-dateutil (>=2.8,<3.0)
Requires-Dist: yaspin (>=1.2.0,<2.0.0)
Project-URL: Repository, https://github.com/ventor-tech/odoo-backup-db-cli
